{"ongoing_trials": {}, "hyperparameters": {"space": [{"class_name": "Int", "config": {"name": "units", "default": null, "conditions": [], "min_value": 8, "max_value": 128, "step": 8, "sampling": "linear"}}], "values": {"units": 8}}, "start_order": ["0", "1", "2", "3", "4"], "end_order": ["0", "1", "2", "2", "3", "4"], "run_times": {"0": 1, "1": 1, "2": 2, "3": 1, "4": 1}, "retry_queue": [], "seed": 9885, "seed_state": 9892, "tried_so_far": ["afbd914529855728f8b8b5da478a4e56", "6c6c7588a891dfd2b3a98d59252c7f19", "ae0a7ec38b29e5bdb4629705d1e71192", "d24b6a4533b58780c944782269c062b3", "b61b0cefe22a0921604e16f01a7be80e"], "id_to_hash": {"0": "ae0a7ec38b29e5bdb4629705d1e71192", "1": "b61b0cefe22a0921604e16f01a7be80e", "2": "d24b6a4533b58780c944782269c062b3", "3": "6c6c7588a891dfd2b3a98d59252c7f19", "4": "afbd914529855728f8b8b5da478a4e56"}, "display": {"search_start": "2025-03-02T23:17:50.783054", "trial_start": {"0": "2025-03-02T23:17:50.783054", "1": "2025-03-02T23:17:51.152062", "2": "2025-03-02T23:17:51.557431", "3": "2025-03-02T23:18:03.752978", "4": "2025-03-02T23:18:06.908934"}, "trial_number": {"0": 1, "1": 2, "2": 3, "3": 4, "4": 5}}}